qucs2gerber/__init__.py
qucs2gerber/__main__.py
qucs2gerber/qucs2gerber.py
qucs2gerber-0.0.4.dist-info/LICENSE
qucs2gerber-0.0.4.dist-info/METADATA
qucs2gerber-0.0.4.dist-info/WHEEL
qucs2gerber-0.0.4.dist-info/top_level.txt
qucs2gerber-0.0.4.dist-info/RECORD
