Metadata-Version: 2.1
Name: qucs2gerber
Version: 0.0.4
Summary: A Qucs to Gerber generation tool.
Home-page: https://github.com/rccarroll654/qucs2gerber
Author: Russell Carroll
Author-email: russell_carroll@carrelec.com
License: UNKNOWN
Platform: UNKNOWN
Classifier: Programming Language :: Python :: 3
Classifier: License :: OSI Approved :: MIT License
Classifier: Operating System :: OS Independent
